{"httpProtocol":"HTTP/1.1","clientAcceptEncoding":"gzip, deflate, br","requestPriority":"","edgeRequestKeepAliveStatus":1,"requestHeaderNames":{},"clientTcpRtt":19,"colo":"SAN","asn":22773,"asOrganization":"Cox Communications Inc.","country":"US","isEUCountry":false,"city":"San Diego","continent":"NA","region":"California","regionCode":"CA","timezone":"America/Los_Angeles","longitude":"-117.16472","latitude":"32.71571","postalCode":"92101","metroCode":"825","tlsVersion":"TLSv1.3","tlsCipher":"AEAD-AES256-GCM-SHA384","tlsClientRandom":"wWf4r/LwkWXY2lMEAkftlBY/Ut2tViLtiqfXxMP53lU=","tlsClientCiphersSha1":"kXrN3VEKDdzz2cPKTQaKzpxVTxQ=","tlsClientExtensionsSha1":"1eY97BUYYO8vDaTfHQywB1pcNdM=","tlsClientExtensionsSha1Le":"u4wtEMFQBY18l3BzHAvORm+KGRw=","tlsExportedAuthenticator":{"clientHandshake":"95597e0fb1f5de600ef2e3ed065abddf475d29cbe277929be672d7d38a9d7fd8ea65c4615bc7303d2129c644e8c3b253","serverHandshake":"5abd3539ca85d8aa565d2ec279304d2a1cb4d4976a21f3e23327f2ebeda2e0b8c0c7e94ef6f2c06ecd69ed05b4762cf6","clientFinished":"f30e3aefd0f6cb73c494af5bd81d8d6dc2cfea575e91a4e439855cf389e193400d72b530604d9711356ae4b43a1e9b3a","serverFinished":"b55f9b39ce6a19dc9c82ce0c11479d235316aaa54cfe55671af7ab687b4d75ba5866ceb6b38b554976bdc6c90b72f0f1"},"tlsClientHelloLength":"1605","tlsClientAuth":{"certPresented":"0","certVerified":"NONE","certRevoked":"0","certIssuerDN":"","certSubjectDN":"","certIssuerDNRFC2253":"","certSubjectDNRFC2253":"","certIssuerDNLegacy":"","certSubjectDNLegacy":"","certSerial":"","certIssuerSerial":"","certSKI":"","certIssuerSKI":"","certFingerprintSHA1":"","certFingerprintSHA256":"","certNotBefore":"","certNotAfter":""},"verifiedBotCategory":"","botManagement":{"corporateProxy":false,"verifiedBot":false,"jsDetection":{"passed":false},"staticResource":false,"detectionIds":{},"score":99}}